ironbeam/__init__.py
ironbeam/base.py
ironbeam/exceptions.py
ironbeam/literals.py
ironbeam/auth/__init__.py
ironbeam/auth/base.py
ironbeam/info/__init__.py
ironbeam/info/base.py
ironbeam/info/models.py
ironbeam/market/__init__.py
ironbeam/market/base.py
ironbeam/market/models.py
ironbeam-0.1.2.dist-info/METADATA
ironbeam-0.1.2.dist-info/WHEEL
ironbeam-0.1.2.dist-info/RECORD
