Metadata-Version: 2.4
Name: ironbeam
Version: 0.1.2
Summary: Add your description here
Author-email: David Mckim <davidmckim@gmail.com>
Requires-Python: >=3.11
Requires-Dist: httpx>=0.28.1
Requires-Dist: pandas>=2.2.3
Requires-Dist: pip>=24.3.1
Requires-Dist: pydantic>=2.10.4
Requires-Dist: tool>=0.8.0
